traefisy/__init__.py
traefisy/main.py
traefisy/utils.py
traefisy/db/__init__.py
traefisy/db/db.py
traefisy/db/models.py
traefisy-0.1.2.dist-info/LICENSE
traefisy-0.1.2.dist-info/METADATA
traefisy-0.1.2.dist-info/WHEEL
traefisy-0.1.2.dist-info/entry_points.txt
traefisy-0.1.2.dist-info/top_level.txt
traefisy-0.1.2.dist-info/RECORD
